pbasex/__init__.py
pbasex/gData.py
pbasex/pbasex.py
pbasex/rBFs.py
pbasex-1.3.0.dist-info/LICENSE.txt
pbasex-1.3.0.dist-info/METADATA
pbasex-1.3.0.dist-info/WHEEL
pbasex-1.3.0.dist-info/top_level.txt
pbasex-1.3.0.dist-info/RECORD
