Metadata-Version: 2.1
Name: pbasex
Version: 1.3.0
Summary: pBASEX algorithm without polar rebinning.
Home-page: https://github.com/e-champenois/CPBASEX
Author: Elio Champenois
Author-email: elio.champenois@gmail.com
License: MIT
Keywords: pbasex,Abel,inversion,cpbasex
Platform: UNKNOWN
Requires-Dist: numpy
Requires-Dist: h5py
Requires-Dist: quadrant
